{
"skeleton": { "hash": "0cWV0tUCSQOHYm8IIV002dG7SHk", "spine": "3.5.37", "width": 720, "height": 1280, "images": "./冰雪皇冠/" },
"bones": [
	{ "name": "root" },
	{ "name": "bone_390", "parent": "root", "x": 1.89, "y": 643.07 },
	{ "name": "wgg", "parent": "bone_390", "x": -3.56, "y": 355.13, "scaleX": 0.875, "scaleY": 0.875 },
	{ "name": "x2", "parent": "wgg", "x": 25.4, "y": 43.61, "scaleX": 1.177, "scaleY": 1.177 },
	{ "name": "xx1_270", "parent": "root", "x": -70.41, "y": 478.47, "scaleX": 1.08, "scaleY": 1.08 },
	{ "name": "xx2_280", "parent": "root", "x": 85.65, "y": 475.95, "scaleX": 1.073, "scaleY": 1.073 }
],
"slots": [
	{ "name": "wgg", "bone": "wgg", "attachment": "wgg" },
	{ "name": "xx1", "bone": "xx1_270", "attachment": "xx1" },
	{ "name": "xx111", "bone": "xx1_270", "attachment": "xx111" },
	{ "name": "xx2", "bone": "xx2_280", "attachment": "xx2" },
	{ "name": "xx222", "bone": "xx2_280", "attachment": "xx222" },
	{ "name": "x1", "bone": "x2", "attachment": "x1" },
	{ "name": "x2", "bone": "x2", "attachment": "x2" }
],
"skins": {
	"default": {
		"wgg": {
			"wgg": { "x": 4.17, "y": 45.05, "scaleX": 1.77, "scaleY": 1.77, "width": 308, "height": 187 }
		},
		"x1": {
			"x1": { "x": -17.33, "y": 17.19, "scaleX": 1.486, "scaleY": 1.486, "width": 325, "height": 178 }
		},
		"x2": {
			"x2": { "x": -17.3, "y": 17.35, "scaleX": 1.49, "scaleY": 1.49, "width": 308, "height": 183 }
		},
		"xx1": {
			"xx1": { "x": -158.08, "y": 67.26, "scaleX": 1.409, "scaleY": 1.409, "width": 72, "height": 35 }
		},
		"xx111": {
			"xx111": { "x": -158.65, "y": 65.13, "scaleX": 1.409, "scaleY": 1.409, "width": 64, "height": 31 }
		},
		"xx2": {
			"xx2": { "x": 144.23, "y": 71.77, "scaleX": 1.409, "scaleY": 1.409, "width": 72, "height": 35 }
		},
		"xx222": {
			"xx222": { "x": 144.25, "y": 69.67, "scaleX": 1.409, "scaleY": 1.409, "width": 64, "height": 31 }
		}
	}
},
"animations": {
	"animation": {
		"slots": {
			"x1": {
				"color": [
					{ "time": 0.3333, "color": "ffffff00" },
					{ "time": 0.6667, "color": "ffffffff" },
					{ "time": 1, "color": "ffffff00" },
					{ "time": 1.3333, "color": "ffffffff" }
				]
			},
			"x2": {
				"color": [
					{ "time": 0, "color": "ffffff00" },
					{ "time": 0.3333, "color": "ffffffff" },
					{ "time": 0.6667, "color": "ffffff00" },
					{ "time": 1, "color": "ffffffff" },
					{ "time": 1.3333, "color": "ffffff00" }
				]
			},
			"xx1": {
				"color": [
					{ "time": 0, "color": "ffffffff", "curve": "stepped" },
					{ "time": 0.1667, "color": "ffffff00", "curve": "stepped" },
					{ "time": 0.3333, "color": "ffffffff", "curve": "stepped" },
					{ "time": 0.5, "color": "ffffff00", "curve": "stepped" },
					{ "time": 0.6667, "color": "ffffffff", "curve": "stepped" },
					{ "time": 0.8333, "color": "ffffff00", "curve": "stepped" },
					{ "time": 1, "color": "ffffffff", "curve": "stepped" },
					{ "time": 1.1667, "color": "ffffff00", "curve": "stepped" },
					{ "time": 1.3333, "color": "ffffffff" }
				]
			},
			"xx2": {
				"color": [
					{ "time": 0, "color": "ffffffff", "curve": "stepped" },
					{ "time": 0.1667, "color": "ffffff00", "curve": "stepped" },
					{ "time": 0.3333, "color": "ffffffff", "curve": "stepped" },
					{ "time": 0.5, "color": "ffffff00", "curve": "stepped" },
					{ "time": 0.6667, "color": "ffffffff", "curve": "stepped" },
					{ "time": 0.8333, "color": "ffffff00", "curve": "stepped" },
					{ "time": 1, "color": "ffffffff", "curve": "stepped" },
					{ "time": 1.1667, "color": "ffffff00", "curve": "stepped" },
					{ "time": 1.3333, "color": "ffffffff" }
				]
			},
			"xx111": {
				"color": [
					{ "time": 0, "color": "ffffff00", "curve": "stepped" },
					{ "time": 0.1667, "color": "ffffffff", "curve": "stepped" },
					{ "time": 0.3333, "color": "ffffff00", "curve": "stepped" },
					{ "time": 0.5, "color": "ffffffff", "curve": "stepped" },
					{ "time": 0.6667, "color": "ffffff00", "curve": "stepped" },
					{ "time": 0.8333, "color": "ffffffff", "curve": "stepped" },
					{ "time": 1, "color": "ffffff00", "curve": "stepped" },
					{ "time": 1.1667, "color": "ffffffff", "curve": "stepped" },
					{ "time": 1.3333, "color": "ffffff00" }
				]
			},
			"xx222": {
				"color": [
					{ "time": 0, "color": "ffffff00", "curve": "stepped" },
					{ "time": 0.1667, "color": "ffffffff", "curve": "stepped" },
					{ "time": 0.3333, "color": "ffffff00", "curve": "stepped" },
					{ "time": 0.5, "color": "ffffffff", "curve": "stepped" },
					{ "time": 0.6667, "color": "ffffff00", "curve": "stepped" },
					{ "time": 0.8333, "color": "ffffffff", "curve": "stepped" },
					{ "time": 1, "color": "ffffff00", "curve": "stepped" },
					{ "time": 1.1667, "color": "ffffffff", "curve": "stepped" },
					{ "time": 1.3333, "color": "ffffff00" }
				]
			}
		},
		"bones": {
			"xx1_270": {
				"rotate": [
					{ "time": 0, "angle": 0, "curve": "stepped" },
					{ "time": 0.1667, "angle": 0, "curve": "stepped" },
					{ "time": 0.3333, "angle": 0, "curve": "stepped" },
					{ "time": 0.5, "angle": 0, "curve": "stepped" },
					{ "time": 0.6667, "angle": 0, "curve": "stepped" },
					{ "time": 0.8333, "angle": 0, "curve": "stepped" },
					{ "time": 1, "angle": 0, "curve": "stepped" },
					{ "time": 1.1667, "angle": 0, "curve": "stepped" },
					{ "time": 1.3333, "angle": 0 }
				],
				"translate": [
					{ "time": 0, "x": 0, "y": 0, "curve": "stepped" },
					{ "time": 0.1667, "x": 0, "y": 0, "curve": "stepped" },
					{ "time": 0.3333, "x": 0, "y": 0, "curve": "stepped" },
					{ "time": 0.5, "x": 0, "y": 0, "curve": "stepped" },
					{ "time": 0.6667, "x": 0, "y": 0, "curve": "stepped" },
					{ "time": 0.8333, "x": 0, "y": 0, "curve": "stepped" },
					{ "time": 1, "x": 0, "y": 0, "curve": "stepped" },
					{ "time": 1.1667, "x": 0, "y": 0, "curve": "stepped" },
					{ "time": 1.3333, "x": 0, "y": 0 }
				],
				"scale": [
					{ "time": 0, "x": 1, "y": 1, "curve": "stepped" },
					{ "time": 0.1667, "x": 1, "y": 1, "curve": "stepped" },
					{ "time": 0.3333, "x": 1, "y": 1, "curve": "stepped" },
					{ "time": 0.5, "x": 1, "y": 1, "curve": "stepped" },
					{ "time": 0.6667, "x": 1, "y": 1, "curve": "stepped" },
					{ "time": 0.8333, "x": 1, "y": 1, "curve": "stepped" },
					{ "time": 1, "x": 1, "y": 1, "curve": "stepped" },
					{ "time": 1.1667, "x": 1, "y": 1, "curve": "stepped" },
					{ "time": 1.3333, "x": 1, "y": 1 }
				]
			},
			"xx2_280": {
				"rotate": [
					{ "time": 0, "angle": 0, "curve": "stepped" },
					{ "time": 0.1667, "angle": 0, "curve": "stepped" },
					{ "time": 0.3333, "angle": 0, "curve": "stepped" },
					{ "time": 0.5, "angle": 0, "curve": "stepped" },
					{ "time": 0.6667, "angle": 0, "curve": "stepped" },
					{ "time": 0.8333, "angle": 0, "curve": "stepped" },
					{ "time": 1, "angle": 0, "curve": "stepped" },
					{ "time": 1.1667, "angle": 0, "curve": "stepped" },
					{ "time": 1.3333, "angle": 0 }
				],
				"translate": [
					{ "time": 0, "x": 0, "y": 0, "curve": "stepped" },
					{ "time": 0.1667, "x": 0, "y": 0, "curve": "stepped" },
					{ "time": 0.3333, "x": 0, "y": 0, "curve": "stepped" },
					{ "time": 0.5, "x": 0, "y": 0, "curve": "stepped" },
					{ "time": 0.6667, "x": 0, "y": 0, "curve": "stepped" },
					{ "time": 0.8333, "x": 0, "y": 0, "curve": "stepped" },
					{ "time": 1, "x": 0, "y": 0, "curve": "stepped" },
					{ "time": 1.1667, "x": 0, "y": 0, "curve": "stepped" },
					{ "time": 1.3333, "x": 0, "y": 0 }
				],
				"scale": [
					{ "time": 0, "x": 1, "y": 1, "curve": "stepped" },
					{ "time": 0.1667, "x": 1, "y": 1, "curve": "stepped" },
					{ "time": 0.3333, "x": 1, "y": 1, "curve": "stepped" },
					{ "time": 0.5, "x": 1, "y": 1, "curve": "stepped" },
					{ "time": 0.6667, "x": 1, "y": 1, "curve": "stepped" },
					{ "time": 0.8333, "x": 1, "y": 1, "curve": "stepped" },
					{ "time": 1, "x": 1, "y": 1, "curve": "stepped" },
					{ "time": 1.1667, "x": 1, "y": 1, "curve": "stepped" },
					{ "time": 1.3333, "x": 1, "y": 1 }
				]
			},
			"x2": {
				"rotate": [
					{ "time": 0, "angle": 0, "curve": "stepped" },
					{ "time": 0.3333, "angle": 0, "curve": "stepped" },
					{ "time": 0.6667, "angle": 0, "curve": "stepped" },
					{ "time": 1, "angle": 0, "curve": "stepped" },
					{ "time": 1.3333, "angle": 0 }
				],
				"translate": [
					{ "time": 0, "x": 0, "y": 0, "curve": "stepped" },
					{ "time": 0.3333, "x": 0, "y": 0, "curve": "stepped" },
					{ "time": 0.6667, "x": 0, "y": 0, "curve": "stepped" },
					{ "time": 1, "x": 0, "y": 0, "curve": "stepped" },
					{ "time": 1.3333, "x": 0, "y": 0 }
				],
				"scale": [
					{ "time": 0, "x": 1, "y": 1, "curve": "stepped" },
					{ "time": 0.3333, "x": 1, "y": 1, "curve": "stepped" },
					{ "time": 0.6667, "x": 1, "y": 1, "curve": "stepped" },
					{ "time": 1, "x": 1, "y": 1, "curve": "stepped" },
					{ "time": 1.3333, "x": 1, "y": 1 }
				]
			}
		}
	}
}
}